DisWebhooker/Base.py
DisWebhooker/__init__.py
DisWebhooker/__main__.py
DisWebhooker/bot.py
DisWebhooker/clients.py
DisWebhooker/command.py
DisWebhooker/commands.py
DisWebhooker/errors.py
DisWebhooker/func.py
DisWebhooker/objs.py
DisWebhooker/webhook.py
DisWebhooker/mkrTree/__init__.py
DisWebhooker/mkrTree/objs.py
DisWebhooker/mkrTree/rander.py
DisWebhooker/mkrTree/tree.py
DisWebhooker-0.2.0.dist-info/LICENCE.txt
DisWebhooker-0.2.0.dist-info/METADATA
DisWebhooker-0.2.0.dist-info/WHEEL
DisWebhooker-0.2.0.dist-info/top_level.txt
DisWebhooker-0.2.0.dist-info/RECORD
