Metadata-Version: 2.1
Name: DisWebhooker
Version: 0.2.0
Summary: this libray for webhooks. to have fun bots and to create discord applications.
Home-page: UNKNOWN
Author: Alawi Hussein Adnan Al Sayegh
Author-email: programming.laboratorys@gmail.com
License: MIT
Keywords: DisWebhooker,webhooker,diswebhook,webbot,webhook,discord,webdiscord
Platform: UNKNOWN
Classifier: Development Status :: 5 - Production/Stable
Classifier: Intended Audience :: Developers
Classifier: Operating System :: Microsoft :: Windows :: Windows 10
Classifier: Operating System :: POSIX
Classifier: License :: OSI Approved :: MIT License
Classifier: Programming Language :: Python :: 3
Requires-Dist: mkrTree
